LICENSE
MANIFEST.in
README.rst
requirements.txt
setup.py
bolbcord/__init__.py
bolbcord/__main__.py
bolbcord/abc.py
bolbcord/activity.py
bolbcord/appinfo.py
bolbcord/application_command.py
bolbcord/asset.py
bolbcord/audit_logs.py
bolbcord/backoff.py
bolbcord/channel.py
bolbcord/client.py
bolbcord/colour.py
bolbcord/components.py
bolbcord/context_managers.py
bolbcord/embeds.py
bolbcord/emoji.py
bolbcord/enums.py
bolbcord/errors.py
bolbcord/file.py
bolbcord/flags.py
bolbcord/gateway.py
bolbcord/guild.py
bolbcord/health_check.py
bolbcord/http.py
bolbcord/integrations.py
bolbcord/interactions.py
bolbcord/invite.py
bolbcord/iterators.py
bolbcord/member.py
bolbcord/mentions.py
bolbcord/message.py
bolbcord/mixins.py
bolbcord/object.py
bolbcord/oggparse.py
bolbcord/opus.py
bolbcord/partial_emoji.py
bolbcord/permissions.py
bolbcord/player.py
bolbcord/py.typed
bolbcord/raw_models.py
bolbcord/reaction.py
bolbcord/role.py
bolbcord/shard.py
bolbcord/stage_instance.py
bolbcord/state.py
bolbcord/sticker.py
bolbcord/team.py
bolbcord/template.py
bolbcord/threads.py
bolbcord/user.py
bolbcord/utils.py
bolbcord/voice_client.py
bolbcord/widget.py
bolbcord.egg-info/PKG-INFO
bolbcord.egg-info/SOURCES.txt
bolbcord.egg-info/dependency_links.txt
bolbcord.egg-info/requires.txt
bolbcord.egg-info/top_level.txt
bolbcord/bin/libopus-0.x64.dll
bolbcord/bin/libopus-0.x86.dll
bolbcord/ext/commands/__init__.py
bolbcord/ext/commands/_types.py
bolbcord/ext/commands/bot.py
bolbcord/ext/commands/cog.py
bolbcord/ext/commands/context.py
bolbcord/ext/commands/converter.py
bolbcord/ext/commands/cooldowns.py
bolbcord/ext/commands/core.py
bolbcord/ext/commands/errors.py
bolbcord/ext/commands/flags.py
bolbcord/ext/commands/help.py
bolbcord/ext/commands/view.py
bolbcord/ext/tasks/__init__.py
bolbcord/types/__init__.py
bolbcord/types/activity.py
bolbcord/types/appinfo.py
bolbcord/types/audit_log.py
bolbcord/types/channel.py
bolbcord/types/components.py
bolbcord/types/embed.py
bolbcord/types/emoji.py
bolbcord/types/gateway.py
bolbcord/types/guild.py
bolbcord/types/integration.py
bolbcord/types/interactions.py
bolbcord/types/invite.py
bolbcord/types/member.py
