Metadata-Version: 2.1
Name: bolbcord
Version: 2.0.0a4
Summary: A Python wrapper for the Discord API forked from discord.py
Home-page: https://github.com/bolbcord/bolbcord
Author: vcokltfre
License: MIT
Project-URL: Documentation, https://bolbcord.readthedocs.io/en/latest/
Project-URL: Issue tracker, https://github.com/bolbcord/bolbcord/issues
Platform: UNKNOWN
Classifier: Development Status :: 5 - Production/Stable
Classifier: License :: OSI Approved :: MIT License
Classifier: Intended Audience :: Developers
Classifier: Natural Language :: English
Classifier: Operating System :: OS Independent
Classifier: Programming Language :: Python :: 3.8
Classifier: Programming Language :: Python :: 3.9
Classifier: Programming Language :: Python :: 3.10
Classifier: Framework :: AsyncIO
Classifier: Framework :: aiohttp
Classifier: Topic :: Internet
Classifier: Topic :: Software Development :: Libraries
Classifier: Topic :: Software Development :: Libraries :: Python Modules
Classifier: Topic :: Utilities
Classifier: Typing :: Typed
Requires-Python: >=3.8.0
Provides-Extra: voice
Provides-Extra: docs
Provides-Extra: speed
License-File: LICENSE
